ixBrowser/__init__.py
ixBrowser/client.py
ixBrowser/tests/__init__.py
ixBrowser/tests/test_ixbrowser.py
ixBrowser/utils/__init__.py
ixBrowser/utils/use_logger.py
ixBrowser-2.0.0.dist-info/LICENSE
ixBrowser-2.0.0.dist-info/METADATA
ixBrowser-2.0.0.dist-info/WHEEL
ixBrowser-2.0.0.dist-info/top_level.txt
ixBrowser-2.0.0.dist-info/RECORD
