Metadata-Version: 2.1
Name: ixBrowser
Version: 2.0.0
Summary: A SDK for ixBrowser
Home-page: https://github.com/ontisme/ixBrowser
Download-URL: https://pypi.org/project/ixBrowser/
Author: Alan Ting & Ontisme
Author-email: alanting0716@gmail.com
License: MIT
Classifier: Programming Language :: Python :: 3.7
Classifier: Programming Language :: Python :: 3.8
Classifier: Programming Language :: Python :: 3.9
Classifier: Programming Language :: Python :: 3.10
Classifier: Programming Language :: Python :: 3.11
Requires-Python: >=3.7
License-File: LICENSE
Requires-Dist: psutil (==5.9.5)
Requires-Dist: requests (==2.31.0)
Requires-Dist: rich (==13.4.2)
Requires-Dist: urllib3 (==1.26.6)
Provides-Extra: dev
Requires-Dist: psutil (==5.9.5) ; extra == 'dev'
Requires-Dist: requests (==2.31.0) ; extra == 'dev'
Requires-Dist: rich (==13.4.2) ; extra == 'dev'
Requires-Dist: urllib3 (==1.26.6) ; extra == 'dev'
Requires-Dist: twine ; extra == 'dev'
Requires-Dist: setuptools ; extra == 'dev'
